orbitalcyber/__init__.py
orbitalcyber/exceptions/__init__.py
orbitalcyber_sdk-0.1.2.dist-info/LICENSE
orbitalcyber_sdk-0.1.2.dist-info/METADATA
orbitalcyber_sdk-0.1.2.dist-info/WHEEL
orbitalcyber_sdk-0.1.2.dist-info/top_level.txt
orbitalcyber_sdk-0.1.2.dist-info/RECORD
